{
    "URL":"https://tbe.taleo.net",

    "page_elements":
        {
            "dropdown": "//a[@class=\"nav-link dropdown-toggle\" and contains(text(),\"My \")]",
            "view": "//a[text()=\"My View\"]",
            "show_more": "//td[text()=\"My Requisitions\"]/following-sibling::td//a[text()=\"Show me more items\"]",
            "detail_loaded": "//td[contains(text(),\"Requisition Information:\")]",
            "hrefs": "//a[contains(@href,\"RequisitionView.jsp\")]",
            "Labor Category": "//td[contains(text(),\"Labor Cat\") or contains(text(),\"Lab Cat\")]/following::b[1]/text()[not(contains(.,\"N/A\"))]"
        },

    "fields": 
        [
            {"Opened Date":"Opened Date"},
            {"Requisition ID":"Requisition ID"},
            {"LCAT":"LCAT"},
            {"Status":"Status"},
            {"TTO Lead Name":"TTO Lead Name"},
            {"TTO Lead Email":"TTO Lead Email"},
            {"Clearance":"Clearance"},
            {"Reason for Opening":"Reason for Opening"},
            {"Location":"Location"},
            {"Travel":"N/A"},
            {"TTO Number":"TTO Number"},
            {"Full/Part Time":"Full/Part Time"},
            {"Legacy Department":"Legacy Department"},
            {"Opening Type":"Opening Type"},
            {"Need by Date":"Need by Date"},
            {"Project Name":"Project Name"},
            {"Labor Category":"Labor Category"}
        ],

    "big_fields":
        [
            {"Description":"Description"},
            {"Requirements":"Requirements"}
        ]
}